drupal_scout_mcp-1.3.0.dist-info/licenses/LICENSE
src/__init__.py
src/drupal_org.py
src/indexer.py
src/prioritizer.py
src/search.py
src/parsers/__init__.py
src/parsers/info.py
src/parsers/php.py
src/parsers/routing.py
src/parsers/services.py
drupal_scout_mcp-1.3.0.dist-info/METADATA
drupal_scout_mcp-1.3.0.dist-info/WHEEL
drupal_scout_mcp-1.3.0.dist-info/top_level.txt
drupal_scout_mcp-1.3.0.dist-info/RECORD
