Metadata-Version: 2.4
Name: drupal-scout-mcp
Version: 1.3.0
Summary: MCP server for discovering Drupal module functionality
Home-page: https://github.com/davo20019/drupal-scout-mcp
Author: David Loor
Author-email: David Loor <davo20019@gmail.com>
Maintainer-email: David Loor <davo20019@gmail.com>
License: MIT
Project-URL: Homepage, https://github.com/davo20019/drupal-scout-mcp
Project-URL: Documentation, https://github.com/davo20019/drupal-scout-mcp#readme
Project-URL: Repository, https://github.com/davo20019/drupal-scout-mcp.git
Project-URL: Issues, https://github.com/davo20019/drupal-scout-mcp/issues
Project-URL: Changelog, https://github.com/davo20019/drupal-scout-mcp/blob/main/CHANGELOG.md
Keywords: drupal,mcp,module,discovery,development
Classifier: Development Status :: 3 - Alpha
Classifier: Intended Audience :: Developers
Classifier: Topic :: Software Development :: Libraries
Classifier: License :: OSI Approved :: MIT License
Classifier: Programming Language :: Python :: 3
Classifier: Programming Language :: Python :: 3.10
Classifier: Programming Language :: Python :: 3.11
Classifier: Programming Language :: Python :: 3.12
Requires-Python: >=3.10
License-File: LICENSE
Requires-Dist: fastmcp>=0.2.0
Requires-Dist: pyyaml>=6.0
Provides-Extra: dev
Requires-Dist: pytest>=7.0.0; extra == "dev"
Requires-Dist: pytest-cov>=4.0.0; extra == "dev"
Requires-Dist: black>=23.0.0; extra == "dev"
Requires-Dist: ruff>=0.1.0; extra == "dev"
Dynamic: author
Dynamic: home-page
Dynamic: license-file
Dynamic: requires-python
